README.md
setup.cfg
setup.py
dsnd_probability_25032020_90489/Binomialdistribution.py
dsnd_probability_25032020_90489/Gaussiandistribution.py
dsnd_probability_25032020_90489/Generaldistribution.py
dsnd_probability_25032020_90489/__init__.py
dsnd_probability_25032020_90489.egg-info/PKG-INFO
dsnd_probability_25032020_90489.egg-info/SOURCES.txt
dsnd_probability_25032020_90489.egg-info/dependency_links.txt
dsnd_probability_25032020_90489.egg-info/not-zip-safe
dsnd_probability_25032020_90489.egg-info/top_level.txt