Metadata-Version: 1.0
Name: dsnd-probability-25032020-90489
Version: 0.1
Summary: Gaussian distributions
Home-page: UNKNOWN
Author: Martin Kolb
Author-email: martinkolb25@googlemail.com
License: UNKNOWN
Platform: UNKNOWN
